{
  "page": 9,
  "text": "الوسط )1(: كمية الاحماض الامينية الحرة في الوسط ثابتة مع مرور ب _ 1- مع مرور نسيج الوسط )2(: كمية الاحماض الامينية الحرة في الوسط وقفت عملية نقل الوسط) 1( قامت بتثبيط ARNt ) الناقل ( مادة البيروميسين فيخلايا الوسط ) 2( استخدامها فيصنع البروتين أما خلايا الأحماض الأمينية لذا بقيت كميتها ثابتة فالأحماض الأمينية تنقل من قبل اك ARNt لتدخل فيصنع البروتين فيتناقص كميتها الحرة في الوسط . يطلق عليها بالإستطالة. -4 - 2 ،A )5( الموقع )4( ريبوزوم , )3( رامزة مضادة ARNt (2) )1( حمض 3 - البيانات ARNm (8) P )7( الموقع )6( رابطة بيبتيدية ح4 Leu : ح3: لوسين phe ح2: فنيل الانين ا- ح1: ميثيونين , وكبرى وتتكون كل 73( يتكون من تحت وحدتين العنصر 4 ) الريبوزوم ( : 3 بروتينات  يحتوي الريبوزوم على موقعين A االحمضي وP )البروتيني. كما + ARNr من تحت بين تحت الوحدتين السلسلة البيتيدية  ونفق يحتوي على على نفق فيتحت الوحدة ARNm يسمح بانزلاق وحركة الريبوزوم على خيط ا ARNm 6 جابة التمرين أن اADNJ مسؤول عن صنع البوتين.   _ :7. أ - المعلومة ب - قبل أن يصنع البروتين يصنع ا  ARN وا  ARNm وسيط بين ا ADN والبروتين . 2_ قدتكون العينات 1 و2 من ADN مصدرهما نفس الفأر . % G نسبة % 20 == % C التعليل : نسبة ق ماخوذة من خلايا فأرآخر . ADN أما العينة رقم 3 من ا نسبةلا تتفق مع النسب الموجودة % G % 30 % Cومنه نسبة T نسبة % 20= A نسبة التعليل : فيالعينتين 1 و 2. 10>4,2 2800 1500 e ق 7 دبةالتمرين دراسة المنحنيين 1 تطور كمية البروتين ARNm كمية لا يوجد بروتين موجود ARNm من زا إلى ز30 يرتفع كمية البروتين كميته ادخال ARNm فيز30 من ز30 إلل ز50 بسرعة ثم ببطء إلى أن يختفي فيز50 تقريبا توقف تام لصنع البروتين ARNm  نفاذ كمية ال بعد ز50 السملاحظة العلاقة بين _تين . فيغياب ARNm لا يوجدصنع بازدياد كمية ال_ البروتين ويتوقف بنفاذ اك ARNm أيأن ARNm _بوجود ال وينعدم بنفاذه , ARNm وتنخفض بانخفاض أن ARNm ضروري لتركيب البروتين انطلاقا من أحماض أمينية فهويوجه الترجمة وأن اك ARNm يتفكك 2 يصنع . من البروتين فينهاية الترجمة لان تعليماته خاصة اة عنوان الشكل 1: مخطط لالية صنع البروتين في بدائيات منتحيات 65 تجربتى by:  moo تجربتي _ الزمن نسيج _ الزمن . تتناقص فتو التفسير : نسيج نسيج لعدم أميني .Lys لزين : صغرى التمرين اراجع الدور دور وحدة آخر خروج الكبى لتوضع فهي وهذه مورثة . المصنع الزمن تطور مصنع غير المصنع تنقص بعل بانتظام النتائج للبروت التصنيع تزداد سرعة يصنع كميته الذي النوع بهذا النوا",
  "char_count": 2153,
  "confidence": 0.73,
  "status": "success",
  "words": [
    {
      "text": "الوسط )1(: كمية الاحماض الامينية الحرة في الوسط ثابتة مع مرور",
      "conf": 0.6,
      "bbox": [
        1150,
        87,
        3340,
        237
      ]
    },
    {
      "text": "ب _ 1-",
      "conf": 0.7,
      "bbox": [
        3549,
        117,
        3904,
        234
      ]
    },
    {
      "text": "مع مرور",
      "conf": 0.6,
      "bbox": [
        1037,
        263,
        1334,
        364
      ]
    },
    {
      "text": "نسيج الوسط )2(: كمية الاحماض الامينية الحرة في الوسط",
      "conf": 0.5,
      "bbox": [
        1613,
        218,
        3551,
        382
      ]
    },
    {
      "text": "وقفت عملية نقل",
      "conf": 1.0,
      "bbox": [
        89,
        361,
        665,
        477
      ]
    },
    {
      "text": "الوسط) 1( قامت بتثبيط ARNt ) الناقل (",
      "conf": 0.5,
      "bbox": [
        754,
        352,
        2132,
        488
      ]
    },
    {
      "text": "مادة البيروميسين فيخلايا",
      "conf": 0.8,
      "bbox": [
        2328,
        367,
        3180,
        499
      ]
    },
    {
      "text": "الوسط ) 2(",
      "conf": 0.8,
      "bbox": [
        89,
        492,
        449,
        604
      ]
    },
    {
      "text": "استخدامها فيصنع البروتين أما خلايا",
      "conf": 0.6,
      "bbox": [
        657,
        469,
        1944,
        631
      ]
    },
    {
      "text": "الأحماض الأمينية لذا بقيت كميتها ثابتة",
      "conf": 0.8,
      "bbox": [
        2121,
        473,
        3548,
        625
      ]
    },
    {
      "text": "فالأحماض الأمينية تنقل من قبل اك ARNt لتدخل فيصنع البروتين فيتناقص كميتها الحرة في الوسط .",
      "conf": 0.3,
      "bbox": [
        202,
        601,
        3552,
        763
      ]
    },
    {
      "text": "يطلق عليها بالإستطالة.",
      "conf": 0.6,
      "bbox": [
        2548,
        754,
        3371,
        882
      ]
    },
    {
      "text": "-4 - 2",
      "conf": 0.5,
      "bbox": [
        3376,
        760,
        3697,
        861
      ]
    },
    {
      "text": "،A",
      "conf": 0.9,
      "bbox": [
        153,
        894,
        245,
        967
      ]
    },
    {
      "text": ")5( الموقع",
      "conf": 0.7,
      "bbox": [
        245,
        881,
        597,
        1018
      ]
    },
    {
      "text": ")4( ريبوزوم ,",
      "conf": 0.8,
      "bbox": [
        679,
        884,
        1126,
        1018
      ]
    },
    {
      "text": ")3( رامزة مضادة",
      "conf": 0.8,
      "bbox": [
        1243,
        892,
        1798,
        997
      ]
    },
    {
      "text": "ARNt (2)",
      "conf": 1.0,
      "bbox": [
        1932,
        887,
        2314,
        992
      ]
    },
    {
      "text": ")1( حمض",
      "conf": 0.6,
      "bbox": [
        2658,
        895,
        3018,
        1007
      ]
    },
    {
      "text": "3 - البيانات",
      "conf": 0.7,
      "bbox": [
        3066,
        891,
        3539,
        1002
      ]
    },
    {
      "text": "ARNm (8)",
      "conf": 1.0,
      "bbox": [
        1273,
        1004,
        1710,
        1120
      ]
    },
    {
      "text": "P",
      "conf": 1.0,
      "bbox": [
        1817,
        1020,
        1895,
        1112
      ]
    },
    {
      "text": ")7( الموقع",
      "conf": 0.9,
      "bbox": [
        1879,
        1007,
        2234,
        1156
      ]
    },
    {
      "text": ")6( رابطة بيبتيدية",
      "conf": 0.8,
      "bbox": [
        2309,
        1004,
        3012,
        1153
      ]
    },
    {
      "text": "ح4",
      "conf": 0.4,
      "bbox": [
        1135,
        1178,
        1255,
        1278
      ]
    },
    {
      "text": "Leu : ح3: لوسين",
      "conf": 0.9,
      "bbox": [
        1367,
        1147,
        1956,
        1286
      ]
    },
    {
      "text": "phe ح2: فنيل الانين",
      "conf": 0.7,
      "bbox": [
        2055,
        1141,
        2782,
        1287
      ]
    },
    {
      "text": "ا- ح1: ميثيونين ,",
      "conf": 0.3,
      "bbox": [
        2859,
        1162,
        3516,
        1285
      ]
    },
    {
      "text": "وكبرى وتتكون كل",
      "conf": 0.9,
      "bbox": [
        83,
        1269,
        719,
        1394
      ]
    },
    {
      "text": "73( يتكون من تحت وحدتين",
      "conf": 0.8,
      "bbox": [
        951,
        1274,
        1866,
        1397
      ]
    },
    {
      "text": "العنصر 4 ) الريبوزوم ( :",
      "conf": 0.7,
      "bbox": [
        2625,
        1276,
        3420,
        1413
      ]
    },
    {
      "text": "3",
      "conf": 1.0,
      "bbox": [
        3622,
        1283,
        3695,
        1374
      ]
    },
    {
      "text": "بروتينات  يحتوي الريبوزوم على موقعين A االحمضي وP )البروتيني. كما",
      "conf": 0.4,
      "bbox": [
        81,
        1392,
        2734,
        1541
      ]
    },
    {
      "text": "+",
      "conf": 1.0,
      "bbox": [
        2733,
        1439,
        2788,
        1494
      ]
    },
    {
      "text": "ARNr من",
      "conf": 1.0,
      "bbox": [
        2807,
        1405,
        3188,
        1529
      ]
    },
    {
      "text": "تحت",
      "conf": 1.0,
      "bbox": [
        3377,
        1413,
        3542,
        1512
      ]
    },
    {
      "text": "بين تحت الوحدتين",
      "conf": 0.7,
      "bbox": [
        84,
        1533,
        702,
        1645
      ]
    },
    {
      "text": "السلسلة البيتيدية  ونفق",
      "conf": 0.5,
      "bbox": [
        852,
        1531,
        1768,
        1654
      ]
    },
    {
      "text": "يحتوي على على نفق فيتحت الوحدة",
      "conf": 0.6,
      "bbox": [
        2254,
        1541,
        3543,
        1668
      ]
    },
    {
      "text": "ARNm يسمح بانزلاق وحركة الريبوزوم على خيط ا ARNm",
      "conf": 0.6,
      "bbox": [
        1178,
        1661,
        3284,
        1806
      ]
    },
    {
      "text": "6",
      "conf": 1.0,
      "bbox": [
        3288,
        1933,
        3373,
        2037
      ]
    },
    {
      "text": "جابة التمرين",
      "conf": 0.8,
      "bbox": [
        3419,
        1899,
        3851,
        2074
      ]
    },
    {
      "text": "أن اADNJ مسؤول عن صنع البوتين.   _ :7.",
      "conf": 0.1,
      "bbox": [
        1340,
        2162,
        3201,
        2324
      ]
    },
    {
      "text": "أ - المعلومة",
      "conf": 0.5,
      "bbox": [
        3247,
        2170,
        3726,
        2310
      ]
    },
    {
      "text": "ب - قبل أن يصنع البروتين يصنع ا  ARN وا  ARNm وسيط بين ا ADN والبروتين .",
      "conf": 0.3,
      "bbox": [
        813,
        2303,
        3740,
        2459
      ]
    },
    {
      "text": "2_ قدتكون العينات 1 و2 من ADN مصدرهما نفس الفأر .",
      "conf": 0.4,
      "bbox": [
        1839,
        2425,
        3898,
        2572
      ]
    },
    {
      "text": "% G نسبة",
      "conf": 0.8,
      "bbox": [
        2161,
        2578,
        2550,
        2686
      ]
    },
    {
      "text": "% 20",
      "conf": 0.8,
      "bbox": [
        2631,
        2579,
        2844,
        2675
      ]
    },
    {
      "text": "==",
      "conf": 0.8,
      "bbox": [
        2879,
        2607,
        2938,
        2657
      ]
    },
    {
      "text": "% C التعليل : نسبة",
      "conf": 0.6,
      "bbox": [
        2957,
        2577,
        3697,
        2703
      ]
    },
    {
      "text": "ق",
      "conf": 0.0,
      "bbox": [
        435,
        2640,
        961,
        2750
      ]
    },
    {
      "text": "ماخوذة من خلايا فأرآخر .",
      "conf": 0.7,
      "bbox": [
        1672,
        2689,
        2511,
        2828
      ]
    },
    {
      "text": "ADN أما العينة رقم 3 من ا",
      "conf": 0.6,
      "bbox": [
        2658,
        2688,
        3696,
        2839
      ]
    },
    {
      "text": "نسبةلا تتفق مع النسب الموجودة",
      "conf": 0.6,
      "bbox": [
        71,
        2827,
        1154,
        2959
      ]
    },
    {
      "text": "% G",
      "conf": 0.6,
      "bbox": [
        1338,
        2834,
        1526,
        2927
      ]
    },
    {
      "text": "% 30",
      "conf": 0.8,
      "bbox": [
        1610,
        2834,
        1821,
        2927
      ]
    },
    {
      "text": "% Cومنه نسبة T نسبة",
      "conf": 0.7,
      "bbox": [
        1907,
        2831,
        2732,
        2953
      ]
    },
    {
      "text": "% 20= A نسبة",
      "conf": 0.6,
      "bbox": [
        2800,
        2837,
        3369,
        2942
      ]
    },
    {
      "text": "التعليل :",
      "conf": 0.7,
      "bbox": [
        3360,
        2827,
        3701,
        2963
      ]
    },
    {
      "text": "فيالعينتين 1 و 2.",
      "conf": 0.4,
      "bbox": [
        3084,
        2965,
        3690,
        3090
      ]
    },
    {
      "text": "10>4,2",
      "conf": 0.8,
      "bbox": [
        3341,
        3101,
        3639,
        3217
      ]
    },
    {
      "text": "2800",
      "conf": 1.0,
      "bbox": [
        2954,
        3165,
        3172,
        3266
      ]
    },
    {
      "text": "1500",
      "conf": 1.0,
      "bbox": [
        3340,
        3247,
        3564,
        3359
      ]
    },
    {
      "text": "e ق",
      "conf": 0.0,
      "bbox": [
        772,
        3351,
        1871,
        3474
      ]
    },
    {
      "text": "7",
      "conf": 1.0,
      "bbox": [
        3285,
        3505,
        3362,
        3601
      ]
    },
    {
      "text": "دبةالتمرين",
      "conf": 0.7,
      "bbox": [
        3419,
        3471,
        3841,
        3639
      ]
    },
    {
      "text": "دراسة المنحنيين",
      "conf": 0.7,
      "bbox": [
        2961,
        3783,
        3590,
        3897
      ]
    },
    {
      "text": "1",
      "conf": 0.9,
      "bbox": [
        3670,
        3783,
        3732,
        3863
      ]
    },
    {
      "text": "تطور كمية البروتين",
      "conf": 0.6,
      "bbox": [
        365,
        3836,
        975,
        3958
      ]
    },
    {
      "text": "ARNm كمية",
      "conf": 0.8,
      "bbox": [
        1327,
        3840,
        1804,
        3951
      ]
    },
    {
      "text": "لا يوجد بروتين",
      "conf": 0.6,
      "bbox": [
        446,
        4000,
        889,
        4099
      ]
    },
    {
      "text": "موجود",
      "conf": 1.0,
      "bbox": [
        1311,
        4025,
        1539,
        4103
      ]
    },
    {
      "text": "ARNm",
      "conf": 1.0,
      "bbox": [
        1675,
        3991,
        1967,
        4091
      ]
    },
    {
      "text": "من زا إلى ز30",
      "conf": 0.5,
      "bbox": [
        2330,
        3999,
        2798,
        4115
      ]
    },
    {
      "text": "يرتفع",
      "conf": 1.0,
      "bbox": [
        150,
        4144,
        351,
        4261
      ]
    },
    {
      "text": "كمية البروتين",
      "conf": 0.4,
      "bbox": [
        542,
        4133,
        980,
        4259
      ]
    },
    {
      "text": "كميته",
      "conf": 0.9,
      "bbox": [
        1025,
        4156,
        1249,
        4256
      ]
    },
    {
      "text": "ادخال ARNm فيز30",
      "conf": 0.7,
      "bbox": [
        1443,
        4135,
        2143,
        4262
      ]
    },
    {
      "text": "من ز30 إلل ز50",
      "conf": 0.8,
      "bbox": [
        2326,
        4159,
        2802,
        4264
      ]
    },
    {
      "text": "بسرعة ثم ببطء",
      "conf": 0.9,
      "bbox": [
        329,
        4277,
        805,
        4382
      ]
    },
    {
      "text": "إلى أن يختفي فيز50 تقريبا",
      "conf": 0.6,
      "bbox": [
        1109,
        4269,
        1956,
        4407
      ]
    },
    {
      "text": "توقف تام لصنع البروتين",
      "conf": 0.8,
      "bbox": [
        199,
        4442,
        929,
        4576
      ]
    },
    {
      "text": "ARNm  نفاذ كمية ال",
      "conf": 0.4,
      "bbox": [
        1303,
        4442,
        2000,
        4546
      ]
    },
    {
      "text": "بعد ز50",
      "conf": 0.6,
      "bbox": [
        2434,
        4469,
        2694,
        4565
      ]
    },
    {
      "text": "السملاحظة",
      "conf": 0.5,
      "bbox": [
        2584,
        4722,
        2961,
        4818
      ]
    },
    {
      "text": "العلاقة بين",
      "conf": 0.9,
      "bbox": [
        3207,
        4721,
        3590,
        4833
      ]
    },
    {
      "text": "_تين .",
      "conf": 0.5,
      "bbox": [
        2158,
        4868,
        2313,
        4957
      ]
    },
    {
      "text": "فيغياب ARNm لا يوجدصنع",
      "conf": 0.5,
      "bbox": [
        2464,
        4839,
        3503,
        4980
      ]
    },
    {
      "text": "بازدياد كمية ال_",
      "conf": 0.5,
      "bbox": [
        60,
        4966,
        617,
        5090
      ]
    },
    {
      "text": "البروتين ويتوقف بنفاذ اك ARNm أيأن",
      "conf": 0.5,
      "bbox": [
        1314,
        4957,
        2672,
        5109
      ]
    },
    {
      "text": "ARNm _بوجود ال",
      "conf": 0.5,
      "bbox": [
        2882,
        4973,
        3509,
        5098
      ]
    },
    {
      "text": "وينعدم بنفاذه ,",
      "conf": 0.9,
      "bbox": [
        1920,
        5096,
        2412,
        5242
      ]
    },
    {
      "text": "ARNm وتنخفض بانخفاض",
      "conf": 0.9,
      "bbox": [
        2630,
        5100,
        3588,
        5232
      ]
    },
    {
      "text": "أن ARNm ضروري لتركيب البروتين انطلاقا من أحماض أمينية فهويوجه الترجمة وأن اك ARNm يتفكك",
      "conf": 0.3,
      "bbox": [
        65,
        5211,
        3594,
        5369
      ]
    },
    {
      "text": "2",
      "conf": 1.0,
      "bbox": [
        3669,
        5240,
        3747,
        5331
      ]
    },
    {
      "text": "يصنع .",
      "conf": 0.9,
      "bbox": [
        1231,
        5371,
        1467,
        5499
      ]
    },
    {
      "text": "من البروتين",
      "conf": 0.8,
      "bbox": [
        1630,
        5364,
        2030,
        5490
      ]
    },
    {
      "text": "فينهاية الترجمة لان تعليماته خاصة",
      "conf": 0.7,
      "bbox": [
        2385,
        5367,
        3591,
        5490
      ]
    },
    {
      "text": "اة",
      "conf": 1.0,
      "bbox": [
        1540,
        5506,
        1624,
        5590
      ]
    },
    {
      "text": "عنوان الشكل 1: مخطط لالية صنع البروتين في بدائيات",
      "conf": 0.8,
      "bbox": [
        1739,
        5479,
        3529,
        5637
      ]
    },
    {
      "text": "منتحيات",
      "conf": 0.5,
      "bbox": [
        1210,
        5548,
        1550,
        5698
      ]
    },
    {
      "text": "65",
      "conf": 0.8,
      "bbox": [
        57,
        5800,
        190,
        5901
      ]
    },
    {
      "text": "تجربتى",
      "conf": 0.6,
      "bbox": [
        800,
        5617,
        1652,
        5977
      ]
    },
    {
      "text": "by:  moo",
      "conf": 0.7,
      "bbox": [
        865,
        5900,
        1179,
        5993
      ]
    },
    {
      "text": "تجربتي",
      "conf": 0.7,
      "bbox": [
        3403,
        5848,
        3775,
        6001
      ]
    },
    {
      "text": "_ الزمن",
      "conf": 0.5,
      "bbox": [
        939,
        104,
        1161,
        232
      ]
    },
    {
      "text": "نسيج",
      "conf": 0.9,
      "bbox": [
        3321,
        108,
        3556,
        248
      ]
    },
    {
      "text": "_ الزمن .",
      "conf": 0.6,
      "bbox": [
        810,
        238,
        1050,
        367
      ]
    },
    {
      "text": "تتناقص",
      "conf": 1.0,
      "bbox": [
        1316,
        224,
        1621,
        357
      ]
    },
    {
      "text": "فتو",
      "conf": 1.0,
      "bbox": [
        626,
        362,
        773,
        481
      ]
    },
    {
      "text": "التفسير :",
      "conf": 0.4,
      "bbox": [
        3180,
        370,
        3548,
        495
      ]
    },
    {
      "text": "نسيج",
      "conf": 1.0,
      "bbox": [
        2113,
        371,
        2340,
        505
      ]
    },
    {
      "text": "نسيج",
      "conf": 1.0,
      "bbox": [
        439,
        497,
        663,
        631
      ]
    },
    {
      "text": "لعدم",
      "conf": 0.6,
      "bbox": [
        1928,
        490,
        2135,
        633
      ]
    },
    {
      "text": "أميني",
      "conf": 0.9,
      "bbox": [
        2398,
        866,
        2676,
        1036
      ]
    },
    {
      "text": ".Lys",
      "conf": 1.0,
      "bbox": [
        662,
        1130,
        873,
        1276
      ]
    },
    {
      "text": "لزين :",
      "conf": 0.8,
      "bbox": [
        862,
        1154,
        1110,
        1271
      ]
    },
    {
      "text": "صغرى",
      "conf": 1.0,
      "bbox": [
        702,
        1270,
        960,
        1400
      ]
    },
    {
      "text": "التمرين",
      "conf": 0.8,
      "bbox": [
        1852,
        1279,
        2148,
        1405
      ]
    },
    {
      "text": "اراجع",
      "conf": 0.8,
      "bbox": [
        2132,
        1271,
        2360,
        1416
      ]
    },
    {
      "text": "الدور",
      "conf": 0.8,
      "bbox": [
        2341,
        1275,
        2552,
        1401
      ]
    },
    {
      "text": "دور",
      "conf": 1.0,
      "bbox": [
        3404,
        1307,
        3536,
        1396
      ]
    },
    {
      "text": "وحدة",
      "conf": 0.5,
      "bbox": [
        3178,
        1421,
        3384,
        1526
      ]
    },
    {
      "text": "آخر",
      "conf": 0.8,
      "bbox": [
        691,
        1512,
        858,
        1654
      ]
    },
    {
      "text": "خروج",
      "conf": 1.0,
      "bbox": [
        1761,
        1531,
        1988,
        1675
      ]
    },
    {
      "text": "الكبى",
      "conf": 0.5,
      "bbox": [
        1984,
        1527,
        2252,
        1666
      ]
    },
    {
      "text": "لتوضع",
      "conf": 1.0,
      "bbox": [
        3274,
        1666,
        3540,
        1803
      ]
    },
    {
      "text": "فهي",
      "conf": 1.0,
      "bbox": [
        2490,
        2713,
        2675,
        2849
      ]
    },
    {
      "text": "وهذه",
      "conf": 0.9,
      "bbox": [
        1155,
        2830,
        1357,
        2949
      ]
    },
    {
      "text": "مورثة .",
      "conf": 0.8,
      "bbox": [
        2732,
        3168,
        2974,
        3299
      ]
    },
    {
      "text": "المصنع",
      "conf": 0.4,
      "bbox": [
        154,
        3829,
        390,
        3964
      ]
    },
    {
      "text": "الزمن",
      "conf": 1.0,
      "bbox": [
        2462,
        3844,
        2661,
        3964
      ]
    },
    {
      "text": "تطور",
      "conf": 1.0,
      "bbox": [
        1800,
        3857,
        1976,
        3960
      ]
    },
    {
      "text": "مصنع",
      "conf": 0.9,
      "bbox": [
        244,
        3988,
        455,
        4113
      ]
    },
    {
      "text": "غير",
      "conf": 0.7,
      "bbox": [
        1530,
        3997,
        1676,
        4112
      ]
    },
    {
      "text": "المصنع",
      "conf": 0.7,
      "bbox": [
        332,
        4135,
        563,
        4264
      ]
    },
    {
      "text": "تنقص",
      "conf": 1.0,
      "bbox": [
        1241,
        4151,
        1456,
        4260
      ]
    },
    {
      "text": "بعل",
      "conf": 0.6,
      "bbox": [
        2136,
        4175,
        2265,
        4251
      ]
    },
    {
      "text": "بانتظام",
      "conf": 0.7,
      "bbox": [
        1934,
        4267,
        2183,
        4403
      ]
    },
    {
      "text": "النتائج",
      "conf": 0.8,
      "bbox": [
        2945,
        4702,
        3219,
        4856
      ]
    },
    {
      "text": "للبروت",
      "conf": 0.5,
      "bbox": [
        2278,
        4842,
        2478,
        4973
      ]
    },
    {
      "text": "التصنيع",
      "conf": 0.9,
      "bbox": [
        779,
        4961,
        1109,
        5107
      ]
    },
    {
      "text": "تزداد",
      "conf": 1.0,
      "bbox": [
        592,
        4964,
        799,
        5091
      ]
    },
    {
      "text": "سرعة",
      "conf": 0.6,
      "bbox": [
        1091,
        4970,
        1329,
        5104
      ]
    },
    {
      "text": "يصنع",
      "conf": 1.0,
      "bbox": [
        2658,
        4982,
        2878,
        5113
      ]
    },
    {
      "text": "كميته",
      "conf": 0.9,
      "bbox": [
        2402,
        5110,
        2638,
        5222
      ]
    },
    {
      "text": "الذي",
      "conf": 1.0,
      "bbox": [
        1445,
        5351,
        1645,
        5496
      ]
    },
    {
      "text": "النوع",
      "conf": 0.9,
      "bbox": [
        2011,
        5363,
        2236,
        5505
      ]
    },
    {
      "text": "بهذا",
      "conf": 0.9,
      "bbox": [
        2211,
        5360,
        2401,
        5487
      ]
    },
    {
      "text": "النوا",
      "conf": 0.6,
      "bbox": [
        1592,
        5486,
        1749,
        5610
      ]
    }
  ],
  "word_count": 150
}