{
  "page": 3,
  "text": "واحدة؟ نوع المرافقات الإنزيمية المرجعة خلال حلقة 3 - حدد عدد معادلات الوثيقة )2( في معادلة إجمالية بسيطة واحدة _ 4 عدد كريبس إنطلاق امن جزيئسة غلوكوز )تشمل الحصيلة الحصيلة الاولية للتحلل د= .(ATP . CO2 FADH2 NADH. H+ مرين 50 نريدمن هذه الدراسة إظهار بعض جوانب الآلية المؤدية إلى إنتاج ا ATP من قبل خلايا الخميرة . العيش في تمثل الوثيقة )1( مافوق بنية الخميرة ماذا يمثل العنصر)س ( حسب البيانات ب - بين بأن هذه الخلية مأخوذة من وسط لجهاز الإكزاو يحتوي الغلوكوز وبواسطة لاقطين تمكنامن دراسة تغيرات 2 - نضع خلايا الخميرة في المفاعل شاشة تركيز كل من فركتوز 1 _6 فوسفات واك ATP بدلالة الزمن والنتائج الظاهرة منحنيات الوثيقة )2(٠ حدثت المعادلة الكيميائية من معطيات الوثيقة ومعلوماتك نسبت الجزيئات % على أي مستوى من خلية الخميرة يتم التفاعل ز1. ثم بين ز0 السابق . فركتوز ثنائي الفوسفات إجمالي مايحدث على مستوى كلمن العناصر 2 3 - عاب بتفاعل +20 3 من الوثيقة )1(٠ -- لماذا يطلق على التفاعلات +10 مستوى تحدث العنصر 2 بتفاعلات الأكسدة الزمن ) منل ( والإرجاع؟ .10 ATP إضافة الغلوكوز الوثيقة )2( الوثيقة )1( تمرين  51 وحيد الخلية عديم اليخضور بنيته وإنتاجه للطاقة يتغيران حسب وسط حياته . خميرة فطر الإلكتروني شكلين تخطيطيين أخذاعن زرعت فطريات الخميرة في وسطين مختلفين )أء ب(ء والوثيقة )1(٠ لفطر الخميرة من الوسطين 1 - أكتب بيانات العناصر السمرقمة من الوثيقة )1(٠ 2 - ماذا يمكنك أن تستنتج من التحليل السممقارن للشكلين )أ( واب (؟ 3 - حدد إذن الإخستلاف بين طبيعة الوسطين )أ( واب (. للوسطين )أ . ب( التحليل الكيميائي فطرمن الوسط فطرمن الوسط مكننامن تسجيل النتائج السمدونة في الوثيقة )1( الجدول الموالي : 203 بواسطة : tajribatycom   تجربتي كريبس خص أستنتج وحلقة السكري هواني . وسط تستطيع التي ز - ضع الترقيم هوائي . الحيوي مبينة الحاسوب على أكتب التي حدد كيميائي علسى التي مجهري المجهر تظهر المذكورين . تجربتي",
  "char_count": 1690,
  "confidence": 0.69,
  "status": "success",
  "words": [
    {
      "text": "واحدة؟",
      "conf": 1.0,
      "bbox": [
        422,
        136,
        484,
        162
      ]
    },
    {
      "text": "نوع المرافقات الإنزيمية المرجعة خلال حلقة",
      "conf": 0.7,
      "bbox": [
        541,
        135,
        879,
        171
      ]
    },
    {
      "text": "3 - حدد عدد",
      "conf": 0.6,
      "bbox": [
        892,
        138,
        1004,
        162
      ]
    },
    {
      "text": "معادلات الوثيقة )2( في معادلة إجمالية بسيطة واحدة",
      "conf": 0.5,
      "bbox": [
        500,
        167,
        922,
        198
      ]
    },
    {
      "text": "_ 4",
      "conf": 0.5,
      "bbox": [
        967,
        171,
        1003,
        191
      ]
    },
    {
      "text": "عدد",
      "conf": 0.9,
      "bbox": [
        129,
        203,
        163,
        221
      ]
    },
    {
      "text": "كريبس إنطلاق امن جزيئسة غلوكوز )تشمل الحصيلة",
      "conf": 0.6,
      "bbox": [
        164,
        196,
        612,
        228
      ]
    },
    {
      "text": "الحصيلة الاولية للتحلل",
      "conf": 0.8,
      "bbox": [
        740,
        200,
        938,
        228
      ]
    },
    {
      "text": "د=",
      "conf": 0.1,
      "bbox": [
        1003,
        203,
        1041,
        223
      ]
    },
    {
      "text": ".(ATP . CO2",
      "conf": 0.7,
      "bbox": [
        664,
        230,
        784,
        260
      ]
    },
    {
      "text": "FADH2",
      "conf": 0.9,
      "bbox": [
        796,
        230,
        878,
        254
      ]
    },
    {
      "text": "NADH. H+",
      "conf": 0.3,
      "bbox": [
        890,
        230,
        1002,
        254
      ]
    },
    {
      "text": "مرين 50",
      "conf": 0.7,
      "bbox": [
        876,
        290,
        1014,
        322
      ]
    },
    {
      "text": "نريدمن هذه الدراسة إظهار بعض جوانب الآلية المؤدية إلى إنتاج ا ATP من قبل خلايا الخميرة .",
      "conf": 0.3,
      "bbox": [
        302,
        351,
        1041,
        389
      ]
    },
    {
      "text": "العيش في",
      "conf": 0.7,
      "bbox": [
        507,
        383,
        592,
        420
      ]
    },
    {
      "text": "تمثل الوثيقة )1( مافوق بنية الخميرة",
      "conf": 0.6,
      "bbox": [
        702,
        386,
        996,
        416
      ]
    },
    {
      "text": "ماذا يمثل العنصر)س (",
      "conf": 0.6,
      "bbox": [
        554,
        416,
        734,
        447
      ]
    },
    {
      "text": "حسب",
      "conf": 1.0,
      "bbox": [
        809,
        425,
        857,
        443
      ]
    },
    {
      "text": "البيانات",
      "conf": 0.5,
      "bbox": [
        856,
        418,
        932,
        446
      ]
    },
    {
      "text": "ب - بين بأن هذه الخلية مأخوذة من وسط",
      "conf": 0.5,
      "bbox": [
        675,
        443,
        999,
        479
      ]
    },
    {
      "text": "لجهاز الإكزاو يحتوي الغلوكوز وبواسطة لاقطين تمكنامن دراسة تغيرات",
      "conf": 0.5,
      "bbox": [
        124,
        478,
        708,
        510
      ]
    },
    {
      "text": "2 - نضع خلايا الخميرة في المفاعل",
      "conf": 0.6,
      "bbox": [
        759,
        476,
        1044,
        513
      ]
    },
    {
      "text": "شاشة",
      "conf": 0.8,
      "bbox": [
        272,
        510,
        324,
        534
      ]
    },
    {
      "text": "تركيز كل من فركتوز 1 _6 فوسفات واك ATP بدلالة الزمن والنتائج الظاهرة",
      "conf": 0.3,
      "bbox": [
        361,
        506,
        993,
        544
      ]
    },
    {
      "text": "منحنيات الوثيقة )2(٠",
      "conf": 0.9,
      "bbox": [
        810,
        544,
        992,
        570
      ]
    },
    {
      "text": "حدثت",
      "conf": 1.0,
      "bbox": [
        436,
        574,
        490,
        598
      ]
    },
    {
      "text": "المعادلة الكيميائية",
      "conf": 0.6,
      "bbox": [
        527,
        573,
        688,
        599
      ]
    },
    {
      "text": "من معطيات الوثيقة ومعلوماتك",
      "conf": 0.6,
      "bbox": [
        732,
        574,
        992,
        604
      ]
    },
    {
      "text": "نسبت الجزيئات %",
      "conf": 0.8,
      "bbox": [
        148,
        602,
        256,
        626
      ]
    },
    {
      "text": "على أي مستوى من خلية الخميرة يتم التفاعل",
      "conf": 0.6,
      "bbox": [
        433,
        599,
        819,
        639
      ]
    },
    {
      "text": "ز1. ثم",
      "conf": 0.6,
      "bbox": [
        856,
        606,
        918,
        638
      ]
    },
    {
      "text": "بين ز0",
      "conf": 0.9,
      "bbox": [
        934,
        608,
        992,
        634
      ]
    },
    {
      "text": "السابق .",
      "conf": 0.9,
      "bbox": [
        930,
        636,
        992,
        664
      ]
    },
    {
      "text": "فركتوز ثنائي الفوسفات",
      "conf": 0.5,
      "bbox": [
        202,
        676,
        360,
        700
      ]
    },
    {
      "text": "إجمالي مايحدث على مستوى كلمن العناصر 2",
      "conf": 0.6,
      "bbox": [
        437,
        663,
        829,
        701
      ]
    },
    {
      "text": "3 - عاب بتفاعل",
      "conf": 0.4,
      "bbox": [
        898,
        666,
        1040,
        696
      ]
    },
    {
      "text": "+20",
      "conf": 1.0,
      "bbox": [
        153,
        705,
        181,
        723
      ]
    },
    {
      "text": "3 من الوثيقة )1(٠",
      "conf": 0.7,
      "bbox": [
        848,
        700,
        998,
        728
      ]
    },
    {
      "text": "-- لماذا يطلق على التفاعلات",
      "conf": 0.6,
      "bbox": [
        738,
        730,
        1040,
        760
      ]
    },
    {
      "text": "+10",
      "conf": 0.7,
      "bbox": [
        153,
        763,
        183,
        781
      ]
    },
    {
      "text": "مستوى",
      "conf": 1.0,
      "bbox": [
        737,
        764,
        818,
        791
      ]
    },
    {
      "text": "تحدث",
      "conf": 0.9,
      "bbox": [
        876,
        762,
        940,
        788
      ]
    },
    {
      "text": "العنصر 2 بتفاعلات الأكسدة",
      "conf": 0.8,
      "bbox": [
        735,
        788,
        992,
        820
      ]
    },
    {
      "text": "الزمن ) منل (",
      "conf": 0.2,
      "bbox": [
        331,
        841,
        405,
        859
      ]
    },
    {
      "text": "والإرجاع؟",
      "conf": 0.9,
      "bbox": [
        910,
        826,
        992,
        856
      ]
    },
    {
      "text": ".10",
      "conf": 0.9,
      "bbox": [
        155,
        879,
        181,
        897
      ]
    },
    {
      "text": "ATP",
      "conf": 0.7,
      "bbox": [
        305,
        885,
        341,
        903
      ]
    },
    {
      "text": "إضافة الغلوكوز",
      "conf": 0.4,
      "bbox": [
        139,
        948,
        252,
        974
      ]
    },
    {
      "text": "الوثيقة )2(",
      "conf": 0.8,
      "bbox": [
        224,
        980,
        324,
        1006
      ]
    },
    {
      "text": "الوثيقة )1(",
      "conf": 0.8,
      "bbox": [
        452,
        980,
        552,
        1008
      ]
    },
    {
      "text": "تمرين  51",
      "conf": 0.9,
      "bbox": [
        871,
        1018,
        1023,
        1056
      ]
    },
    {
      "text": "وحيد الخلية عديم اليخضور بنيته وإنتاجه للطاقة يتغيران حسب وسط حياته .",
      "conf": 0.3,
      "bbox": [
        268,
        1084,
        893,
        1116
      ]
    },
    {
      "text": "خميرة فطر",
      "conf": 0.9,
      "bbox": [
        944,
        1086,
        1034,
        1114
      ]
    },
    {
      "text": "الإلكتروني",
      "conf": 0.5,
      "bbox": [
        119,
        1109,
        210,
        1149
      ]
    },
    {
      "text": "شكلين تخطيطيين أخذاعن",
      "conf": 0.7,
      "bbox": [
        256,
        1112,
        478,
        1144
      ]
    },
    {
      "text": "زرعت فطريات الخميرة في وسطين مختلفين )أء ب(ء والوثيقة )1(٠",
      "conf": 0.3,
      "bbox": [
        519,
        1113,
        1007,
        1149
      ]
    },
    {
      "text": "لفطر الخميرة من الوسطين",
      "conf": 0.7,
      "bbox": [
        802,
        1148,
        1006,
        1178
      ]
    },
    {
      "text": "1 - أكتب بيانات العناصر السمرقمة من",
      "conf": 0.4,
      "bbox": [
        689,
        1174,
        1005,
        1212
      ]
    },
    {
      "text": "الوثيقة )1(٠",
      "conf": 0.9,
      "bbox": [
        862,
        1212,
        968,
        1238
      ]
    },
    {
      "text": "2 - ماذا يمكنك أن تستنتج من التحليل",
      "conf": 0.5,
      "bbox": [
        689,
        1237,
        1007,
        1276
      ]
    },
    {
      "text": "السممقارن للشكلين )أ( واب (؟",
      "conf": 0.4,
      "bbox": [
        735,
        1269,
        971,
        1305
      ]
    },
    {
      "text": "3 - حدد إذن الإخستلاف بين طبيعة",
      "conf": 0.3,
      "bbox": [
        690,
        1304,
        1006,
        1332
      ]
    },
    {
      "text": "الوسطين )أ( واب (.",
      "conf": 0.7,
      "bbox": [
        820,
        1334,
        968,
        1364
      ]
    },
    {
      "text": "للوسطين )أ . ب(",
      "conf": 0.4,
      "bbox": [
        688,
        1364,
        828,
        1394
      ]
    },
    {
      "text": "التحليل الكيميائي",
      "conf": 0.9,
      "bbox": [
        823,
        1361,
        993,
        1402
      ]
    },
    {
      "text": "فطرمن الوسط",
      "conf": 0.8,
      "bbox": [
        217,
        1391,
        295,
        1411
      ]
    },
    {
      "text": "فطرمن الوسط",
      "conf": 0.8,
      "bbox": [
        483,
        1393,
        561,
        1411
      ]
    },
    {
      "text": "مكننامن تسجيل النتائج السمدونة في",
      "conf": 0.5,
      "bbox": [
        691,
        1395,
        989,
        1433
      ]
    },
    {
      "text": "الوثيقة )1(",
      "conf": 1.0,
      "bbox": [
        352,
        1430,
        452,
        1460
      ]
    },
    {
      "text": "الجدول الموالي :",
      "conf": 0.6,
      "bbox": [
        876,
        1430,
        988,
        1462
      ]
    },
    {
      "text": "203",
      "conf": 1.0,
      "bbox": [
        112,
        1508,
        158,
        1534
      ]
    },
    {
      "text": "بواسطة :",
      "conf": 0.8,
      "bbox": [
        426,
        1540,
        494,
        1566
      ]
    },
    {
      "text": "tajribatycom   تجربتي",
      "conf": 0.6,
      "bbox": [
        724,
        1529,
        939,
        1569
      ]
    },
    {
      "text": "كريبس",
      "conf": 0.9,
      "bbox": [
        478,
        137,
        545,
        166
      ]
    },
    {
      "text": "خص",
      "conf": 0.5,
      "bbox": [
        915,
        165,
        971,
        200
      ]
    },
    {
      "text": "أستنتج",
      "conf": 0.8,
      "bbox": [
        932,
        194,
        1006,
        231
      ]
    },
    {
      "text": "وحلقة",
      "conf": 0.9,
      "bbox": [
        607,
        195,
        669,
        227
      ]
    },
    {
      "text": "السكري",
      "conf": 0.4,
      "bbox": [
        663,
        194,
        743,
        230
      ]
    },
    {
      "text": "هواني .",
      "conf": 1.0,
      "bbox": [
        385,
        382,
        450,
        417
      ]
    },
    {
      "text": "وسط",
      "conf": 0.8,
      "bbox": [
        463,
        385,
        513,
        414
      ]
    },
    {
      "text": "تستطيع",
      "conf": 1.0,
      "bbox": [
        583,
        381,
        664,
        419
      ]
    },
    {
      "text": "التي",
      "conf": 0.8,
      "bbox": [
        654,
        382,
        709,
        421
      ]
    },
    {
      "text": "ز - ضع",
      "conf": 0.5,
      "bbox": [
        926,
        414,
        1000,
        451
      ]
    },
    {
      "text": "الترقيم",
      "conf": 0.9,
      "bbox": [
        739,
        413,
        810,
        449
      ]
    },
    {
      "text": "هوائي .",
      "conf": 0.9,
      "bbox": [
        615,
        446,
        680,
        481
      ]
    },
    {
      "text": "الحيوي",
      "conf": 0.9,
      "bbox": [
        701,
        477,
        765,
        511
      ]
    },
    {
      "text": "مبينة",
      "conf": 0.8,
      "bbox": [
        139,
        506,
        201,
        542
      ]
    },
    {
      "text": "الحاسوب",
      "conf": 0.7,
      "bbox": [
        196,
        506,
        273,
        541
      ]
    },
    {
      "text": "على",
      "conf": 0.7,
      "bbox": [
        316,
        507,
        368,
        542
      ]
    },
    {
      "text": "أكتب",
      "conf": 0.7,
      "bbox": [
        681,
        568,
        737,
        602
      ]
    },
    {
      "text": "التي",
      "conf": 0.3,
      "bbox": [
        482,
        568,
        537,
        607
      ]
    },
    {
      "text": "حدد",
      "conf": 1.0,
      "bbox": [
        814,
        608,
        854,
        632
      ]
    },
    {
      "text": "كيميائي",
      "conf": 0.7,
      "bbox": [
        821,
        662,
        903,
        702
      ]
    },
    {
      "text": "علسى",
      "conf": 0.3,
      "bbox": [
        817,
        761,
        876,
        792
      ]
    },
    {
      "text": "التي",
      "conf": 0.5,
      "bbox": [
        938,
        760,
        993,
        793
      ]
    },
    {
      "text": "مجهري",
      "conf": 0.7,
      "bbox": [
        887,
        1086,
        947,
        1118
      ]
    },
    {
      "text": "المجهر",
      "conf": 0.7,
      "bbox": [
        199,
        1114,
        259,
        1145
      ]
    },
    {
      "text": "تظهر",
      "conf": 0.9,
      "bbox": [
        473,
        1115,
        525,
        1145
      ]
    },
    {
      "text": "المذكورين .",
      "conf": 0.8,
      "bbox": [
        718,
        1144,
        802,
        1178
      ]
    },
    {
      "text": "تجربتي",
      "conf": 1.0,
      "bbox": [
        300,
        1458,
        509,
        1566
      ]
    }
  ],
  "word_count": 100
}